LICENSE
MANIFEST.in
README.rst
setup.py
django_floppymodelforms.egg-info/PKG-INFO
django_floppymodelforms.egg-info/SOURCES.txt
django_floppymodelforms.egg-info/dependency_links.txt
django_floppymodelforms.egg-info/not-zip-safe
django_floppymodelforms.egg-info/requires.txt
django_floppymodelforms.egg-info/top_level.txt
floppymodelforms/__init__.py
floppymodelforms/models.py