Metadata-Version: 1.1
Name: django-floppymodelforms
Version: 0.1.0
Summary: A hack to force Django's ModelForm to use floppyforms' fields.
Home-page: https://github.com/henriquebastos/django-floppymodelforms
Author: Henrique Bastos
Author-email: henrique@bastos.net
License: BSD
Keywords: floppymodelforms floppy forms django
Platform: UNKNOWN
Classifier: Framework :: Django
Classifier: Intended Audience :: Developers
Classifier: License :: OSI Approved :: BSD License
Classifier: Natural Language :: English
Classifier: Programming Language :: Python :: 2
Classifier: Programming Language :: Python :: 2.7
Classifier: Programming Language :: Python :: 3
Classifier: Programming Language :: Python :: 3.3
